salesforce_toolkit/__init__.py
salesforce_toolkit-1.1.1.dist-info/licenses/LICENSE
salesforce_toolkit-1.1.1.dist-info/METADATA
salesforce_toolkit-1.1.1.dist-info/WHEEL
salesforce_toolkit-1.1.1.dist-info/top_level.txt
salesforce_toolkit-1.1.1.dist-info/RECORD
