Metadata-Version: 2.4
Name: salesforce-toolkit
Version: 1.1.1
Summary: DEPRECATED - Please use 'kinetic-core' instead.
Home-page: https://github.com/antonio-backend-projects/salesforce-toolkit
Author: Antonio Trento
Author-email: info@antoniotrento.net
Classifier: Development Status :: 7 - Inactive
Classifier: Intended Audience :: Developers
Classifier: License :: OSI Approved :: MIT License
Classifier: Programming Language :: Python :: 3
Requires-Python: >=3.8
License-File: LICENSE
Requires-Dist: kinetic-core
Dynamic: author
Dynamic: author-email
Dynamic: classifier
Dynamic: description
Dynamic: description-content-type
Dynamic: home-page
Dynamic: license-file
Dynamic: requires-dist
Dynamic: requires-python
Dynamic: summary
